{
    "@context": "https://kanazawabunko-db.pen-kanagawa.ed.jp/api-context",
    "@id": "https://kanazawabunko-db.pen-kanagawa.ed.jp/api/properties/1155",
    "@type": "o:Property",
    "o:comment": "The person or organization who produced the work (e.g. music album, movie, tv/radio series etc.).",
    "o:id": 1155,
    "o:label": "producer",
    "o:local_name": "producer",
    "o:term": "schema:producer",
    "o:vocabulary": {
        "@id": "https://kanazawabunko-db.pen-kanagawa.ed.jp/api/vocabularies/7",
        "o:id": 7
    }
}