{
    "@context": "https://kanazawabunko-db.pen-kanagawa.ed.jp/api-context",
    "@id": "https://kanazawabunko-db.pen-kanagawa.ed.jp/api/properties/1347",
    "@type": "o:Property",
    "o:comment": "A sub property of location. The sports event where this action occurred.",
    "o:id": 1347,
    "o:label": "sportsEvent",
    "o:local_name": "sportsEvent",
    "o:term": "schema:sportsEvent",
    "o:vocabulary": {
        "@id": "https://kanazawabunko-db.pen-kanagawa.ed.jp/api/vocabularies/7",
        "o:id": 7
    }
}