{
    "@context": "https://kanazawabunko-db.pen-kanagawa.ed.jp/api-context",
    "@id": "https://kanazawabunko-db.pen-kanagawa.ed.jp/api/properties/1475",
    "@type": "o:Property",
    "o:comment": "Indicates the name of the PropertyValueSpecification to be used in URL templates and form encoding in a manner analogous to HTML's input@name.",
    "o:id": 1475,
    "o:label": "valueName",
    "o:local_name": "valueName",
    "o:term": "schema:valueName",
    "o:vocabulary": {
        "@id": "https://kanazawabunko-db.pen-kanagawa.ed.jp/api/vocabularies/7",
        "o:id": 7
    }
}