{
    "@context": "https://kanazawabunko-db.pen-kanagawa.ed.jp/api-context",
    "@id": "https://kanazawabunko-db.pen-kanagawa.ed.jp/api/media/1608",
    "@type": [
        "o:Media",
        "ex:image"
    ],
    "data": {
        "dimensions": {
            "large": {
                "height": 531,
                "width": 800
            },
            "medium": {
                "height": 266,
                "width": 400
            },
            "original": {
                "height": 1593,
                "width": 2400
            },
            "square": {
                "height": 200,
                "width": 200
            }
        },
        "tile": {
            "deepzoom": {
                "format": "jpg",
                "media_path": "ae132b74d7a927ec58d97ce7f6858e569838a659_files",
                "metadata_path": "ae132b74d7a927ec58d97ce7f6858e569838a659.dzi",
                "overlap": 0,
                "path_base": "/var/www/html/files/tile",
                "size": 256,
                "source": {
                    "height": 1593,
                    "width": 2400
                },
                "tile_type": "deepzoom",
                "total": null,
                "url_base": "https://kanazawabunko-db.pen-kanagawa.ed.jp/files/tile",
                "url_query": ""
            },
            "tiled_tiff": {
                "format": "tif",
                "media_path": "ae132b74d7a927ec58d97ce7f6858e569838a659.tif",
                "metadata_path": null,
                "overlap": 0,
                "path_base": "/var/www/html/files/tile",
                "size": 256,
                "source": {
                    "height": 1593,
                    "width": 2400
                },
                "tile_type": "tiled_tiff",
                "total": null,
                "url_base": "https://kanazawabunko-db.pen-kanagawa.ed.jp/files/tile",
                "url_query": ""
            }
        }
    },
    "dcterms:title": [
        {
            "@value": "金沢貞顕書状（紙背）",
            "is_public": true,
            "property_id": 1,
            "property_label": "Title",
            "type": "literal"
        }
    ],
    "o:alt_text": null,
    "o:created": {
        "@type": "http://www.w3.org/2001/XMLSchema#dateTime",
        "@value": "2022-03-31T10:16:17+00:00"
    },
    "o:filename": "ae132b74d7a927ec58d97ce7f6858e569838a659.jpg",
    "o:id": 1608,
    "o:ingester": "url",
    "o:is_public": true,
    "o:item": {
        "@id": "https://kanazawabunko-db.pen-kanagawa.ed.jp/api/items/288",
        "o:id": 288
    },
    "o:lang": null,
    "o:media_type": "image/jpeg",
    "o:modified": {
        "@type": "http://www.w3.org/2001/XMLSchema#dateTime",
        "@value": "2022-03-31T10:16:17+00:00"
    },
    "o:original_url": "https://kanazawabunko-db.pen-kanagawa.ed.jp/files/original/ae132b74d7a927ec58d97ce7f6858e569838a659.jpg",
    "o:owner": {
        "@id": "https://kanazawabunko-db.pen-kanagawa.ed.jp/api/users/1",
        "o:id": 1
    },
    "o:renderer": "file",
    "o:resource_class": {
        "@id": "https://kanazawabunko-db.pen-kanagawa.ed.jp/api/resource_classes/109",
        "o:id": 109
    },
    "o:resource_template": {
        "@id": "https://kanazawabunko-db.pen-kanagawa.ed.jp/api/resource_templates/1",
        "o:id": 1
    },
    "o:sha256": "915787465b9169b6f8e4f0e27d64a6212a2ed193770b7a07a504a49a6a9a5900",
    "o:size": 287693,
    "o:source": "https://admin_kanazawabunko:b1beeswg8m2eiz0wv5v2@www.kanazawabunko.pref.kanagawa.jp.il3c.com/files/kanazawabunko-images-compressed/287-2.jpg",
    "o:thumbnail": null,
    "o:thumbnail_urls": {
        "large": "https://kanazawabunko-db.pen-kanagawa.ed.jp/files/large/ae132b74d7a927ec58d97ce7f6858e569838a659.jpg",
        "medium": "https://kanazawabunko-db.pen-kanagawa.ed.jp/files/medium/ae132b74d7a927ec58d97ce7f6858e569838a659.jpg",
        "square": "https://kanazawabunko-db.pen-kanagawa.ed.jp/files/square/ae132b74d7a927ec58d97ce7f6858e569838a659.jpg"
    },
    "o:title": "金沢貞顕書状（紙背）",
    "thumbnail_display_urls": {
        "large": "https://kanazawabunko-db.pen-kanagawa.ed.jp/files/large/ae132b74d7a927ec58d97ce7f6858e569838a659.jpg",
        "medium": "https://kanazawabunko-db.pen-kanagawa.ed.jp/files/medium/ae132b74d7a927ec58d97ce7f6858e569838a659.jpg",
        "square": "https://kanazawabunko-db.pen-kanagawa.ed.jp/files/square/ae132b74d7a927ec58d97ce7f6858e569838a659.jpg"
    }
}