{
    "@context": "https://kanazawabunko-db.pen-kanagawa.ed.jp/api-context",
    "@id": "https://kanazawabunko-db.pen-kanagawa.ed.jp/api/media/2176",
    "@type": [
        "o:Media",
        "ex:image"
    ],
    "data": {
        "dimensions": {
            "large": {
                "height": 533,
                "width": 800
            },
            "medium": {
                "height": 267,
                "width": 400
            },
            "original": {
                "height": 1600,
                "width": 2400
            },
            "square": {
                "height": 200,
                "width": 200
            }
        },
        "tile": {
            "deepzoom": {
                "format": "jpg",
                "media_path": "d3ef66c8766b128f331b61e02aed03a3a1cde563_files",
                "metadata_path": "d3ef66c8766b128f331b61e02aed03a3a1cde563.dzi",
                "overlap": 0,
                "path_base": "/var/www/html/files/tile",
                "size": 256,
                "source": {
                    "height": 1600,
                    "width": 2400
                },
                "tile_type": "deepzoom",
                "total": null,
                "url_base": "https://kanazawabunko-db.pen-kanagawa.ed.jp/files/tile",
                "url_query": ""
            },
            "tiled_tiff": {
                "format": "tif",
                "media_path": "d3ef66c8766b128f331b61e02aed03a3a1cde563.tif",
                "metadata_path": null,
                "overlap": 0,
                "path_base": "/var/www/html/files/tile",
                "size": 256,
                "source": {
                    "height": 1600,
                    "width": 2400
                },
                "tile_type": "tiled_tiff",
                "total": null,
                "url_base": "https://kanazawabunko-db.pen-kanagawa.ed.jp/files/tile",
                "url_query": ""
            }
        }
    },
    "dcterms:title": [
        {
            "@value": "大外記清原教元書状",
            "is_public": true,
            "property_id": 1,
            "property_label": "Title",
            "type": "literal"
        }
    ],
    "o:alt_text": null,
    "o:created": {
        "@type": "http://www.w3.org/2001/XMLSchema#dateTime",
        "@value": "2022-03-31T10:39:06+00:00"
    },
    "o:filename": "d3ef66c8766b128f331b61e02aed03a3a1cde563.jpg",
    "o:id": 2176,
    "o:ingester": "url",
    "o:is_public": true,
    "o:item": {
        "@id": "https://kanazawabunko-db.pen-kanagawa.ed.jp/api/items/552",
        "o:id": 552
    },
    "o:lang": null,
    "o:media_type": "image/jpeg",
    "o:modified": {
        "@type": "http://www.w3.org/2001/XMLSchema#dateTime",
        "@value": "2022-03-31T10:39:06+00:00"
    },
    "o:original_url": "https://kanazawabunko-db.pen-kanagawa.ed.jp/files/original/d3ef66c8766b128f331b61e02aed03a3a1cde563.jpg",
    "o:owner": {
        "@id": "https://kanazawabunko-db.pen-kanagawa.ed.jp/api/users/1",
        "o:id": 1
    },
    "o:renderer": "file",
    "o:resource_class": {
        "@id": "https://kanazawabunko-db.pen-kanagawa.ed.jp/api/resource_classes/109",
        "o:id": 109
    },
    "o:resource_template": {
        "@id": "https://kanazawabunko-db.pen-kanagawa.ed.jp/api/resource_templates/1",
        "o:id": 1
    },
    "o:sha256": "4a6f63e97a779f557044044a2a5d66d209e45efe35e8c480217f477d282b898c",
    "o:size": 427667,
    "o:source": "https://admin_kanazawabunko:b1beeswg8m2eiz0wv5v2@www.kanazawabunko.pref.kanagawa.jp.il3c.com/files/kanazawabunko-images-compressed/555-1.jpg",
    "o:thumbnail": null,
    "o:thumbnail_urls": {
        "large": "https://kanazawabunko-db.pen-kanagawa.ed.jp/files/large/d3ef66c8766b128f331b61e02aed03a3a1cde563.jpg",
        "medium": "https://kanazawabunko-db.pen-kanagawa.ed.jp/files/medium/d3ef66c8766b128f331b61e02aed03a3a1cde563.jpg",
        "square": "https://kanazawabunko-db.pen-kanagawa.ed.jp/files/square/d3ef66c8766b128f331b61e02aed03a3a1cde563.jpg"
    },
    "o:title": "大外記清原教元書状",
    "thumbnail_display_urls": {
        "large": "https://kanazawabunko-db.pen-kanagawa.ed.jp/files/large/d3ef66c8766b128f331b61e02aed03a3a1cde563.jpg",
        "medium": "https://kanazawabunko-db.pen-kanagawa.ed.jp/files/medium/d3ef66c8766b128f331b61e02aed03a3a1cde563.jpg",
        "square": "https://kanazawabunko-db.pen-kanagawa.ed.jp/files/square/d3ef66c8766b128f331b61e02aed03a3a1cde563.jpg"
    }
}