{
    "@context": "https://kanazawabunko-db.pen-kanagawa.ed.jp/api-context",
    "@id": "https://kanazawabunko-db.pen-kanagawa.ed.jp/api/items/273",
    "@type": [
        "o:Item",
        "ex:missive"
    ],
    "dcterms:identifier": [
        {
            "@value": "645",
            "is_public": true,
            "property_id": 10,
            "property_label": "Identifier",
            "type": "literal"
        }
    ],
    "dcterms:modified": [
        {
            "@value": "12-Jan-20",
            "is_public": true,
            "property_id": 24,
            "property_label": "Date Modified",
            "type": "literal"
        }
    ],
    "dcterms:title": [
        {
            "@value": "金沢貞顕書状",
            "is_public": true,
            "property_id": 1,
            "property_label": "Title",
            "type": "literal"
        }
    ],
    "ex:age": [
        {
            "@value": "鎌倉時代後期",
            "is_public": true,
            "property_id": 214,
            "property_label": "成立",
            "type": "literal"
        }
    ],
    "ex:deficit": [
        {
            "@value": "前欠",
            "is_public": true,
            "property_id": 199,
            "property_label": "欠損",
            "type": "literal"
        }
    ],
    "ex:figure": [
        {
            "@value": "竪紙（本紙）",
            "is_public": true,
            "property_id": 202,
            "property_label": "形状",
            "type": "literal"
        }
    ],
    "ex:ibun": [
        {
            "@value": "鎌29177",
            "is_public": true,
            "property_id": 210,
            "property_label": "遺文",
            "type": "literal"
        }
    ],
    "ex:japaneseCalendarYear": [
        {
            "@value": "元徳１",
            "is_public": true,
            "property_id": 212,
            "property_label": "和暦",
            "type": "literal"
        }
    ],
    "ex:kanagawakenshi": [
        {
            "@value": "2440",
            "is_public": true,
            "property_id": 208,
            "property_label": "神奈川県史",
            "type": "literal"
        }
    ],
    "ex:kinbunbango": [
        {
            "@value": "348",
            "is_public": true,
            "property_id": 207,
            "property_label": "金文番号",
            "type": "literal"
        }
    ],
    "ex:medium": [
        {
            "@value": "楮紙",
            "is_public": true,
            "property_id": 203,
            "property_label": "料紙",
            "type": "literal"
        }
    ],
    "ex:note": [
        {
            "@value": "金沢貞顕自筆。",
            "is_public": true,
            "property_id": 201,
            "property_label": "付加情報",
            "type": "literal"
        }
    ],
    "ex:seiribango": [
        {
            "@value": "645",
            "is_public": true,
            "property_id": 209,
            "property_label": "整理番号",
            "type": "literal"
        }
    ],
    "ex:sequence": [
        {
            "@value": "K400/S697「金沢貞顕書状」へ接続。",
            "is_public": true,
            "property_id": 196,
            "property_label": "連続情報",
            "type": "literal"
        }
    ],
    "ex:shihai": [
        {
            "@value": "『甫文口伝抄』巻二第7紙（奥書あり）",
            "is_public": true,
            "property_id": 200,
            "property_label": "紙背",
            "type": "literal"
        }
    ],
    "ex:subject": [
        {
            "@value": "金沢貞顕書状",
            "is_public": true,
            "property_id": 205,
            "property_label": "史料名",
            "type": "literal"
        }
    ],
    "ex:transcript": [
        {
            "@value": "　　　　祭に、春日社（大和国）・長谷寺（大和国）等\r\n　　　　参詣之由承候了、特喜思給候也、\r\n　　　　北方（常葉範貞）春日社へ参詣之旨承候、\r\n　　　　実事候哉、可承存候、\r\n　　八月十四日両通御状、菊地入道\r\n　　下向之便、一昨日〈六日〉下着候了、\r\n一、筑後前司貞知（小田）一瓶持参之間、\r\n　　常陸前司（小田時知）・伊勢前司（伊賀兼光）・斎藤左衛門大夫（基明）・\r\n　　松田掃部允（頼済）等参入之由承候了、\r\n　　悦思給候、\r\n一、縫殿頭（長井貞重）同持参之時、出羽左近大夫\r\n　　入道丹後前司（長井宗衡）・小早川安藝前司・水谷（秀有）\r\n　　兵衛蔵人佐々木源太左衛門等同参\r\n　　之間、承候了、縫殿頭所存不審候、",
            "is_public": true,
            "property_id": 218,
            "property_label": "transcript",
            "type": "literal"
        }
    ],
    "ex:volume": [
        {
            "@value": "1通",
            "is_public": true,
            "property_id": 215,
            "property_label": "紙数",
            "type": "literal"
        },
        {
            "@value": "1紙",
            "is_public": true,
            "property_id": 215,
            "property_label": "紙数",
            "type": "literal"
        }
    ],
    "o:created": {
        "@type": "http://www.w3.org/2001/XMLSchema#dateTime",
        "@value": "2022-03-31T07:24:48+00:00"
    },
    "o:id": 273,
    "o:is_public": true,
    "o:item_set": [],
    "o:media": [
        {
            "@id": "https://kanazawabunko-db.pen-kanagawa.ed.jp/api/media/1577",
            "o:id": 1577
        },
        {
            "@id": "https://kanazawabunko-db.pen-kanagawa.ed.jp/api/media/1578",
            "o:id": 1578
        }
    ],
    "o:modified": {
        "@type": "http://www.w3.org/2001/XMLSchema#dateTime",
        "@value": "2022-05-30T01:11:18+00:00"
    },
    "o:owner": {
        "@id": "https://kanazawabunko-db.pen-kanagawa.ed.jp/api/users/1",
        "o:id": 1
    },
    "o:resource_class": {
        "@id": "https://kanazawabunko-db.pen-kanagawa.ed.jp/api/resource_classes/108",
        "o:id": 108
    },
    "o:resource_template": null,
    "o:site": [
        {
            "@id": "https://kanazawabunko-db.pen-kanagawa.ed.jp/api/sites/1",
            "o:id": 1
        }
    ],
    "o:thumbnail": null,
    "o:title": "金沢貞顕書状",
    "thumbnail_display_urls": {
        "large": "https://kanazawabunko-db.pen-kanagawa.ed.jp/files/large/3ba0042c44c0b63708938a9b420ffbac03c9b0c4.jpg",
        "medium": "https://kanazawabunko-db.pen-kanagawa.ed.jp/files/medium/3ba0042c44c0b63708938a9b420ffbac03c9b0c4.jpg",
        "square": "https://kanazawabunko-db.pen-kanagawa.ed.jp/files/square/3ba0042c44c0b63708938a9b420ffbac03c9b0c4.jpg"
    }
}