{
    "@context": "https://kanazawabunko-db.pen-kanagawa.ed.jp/api-context",
    "@id": "https://kanazawabunko-db.pen-kanagawa.ed.jp/api/properties/1290",
    "@type": "o:Property",
    "o:comment": "The number of persons that can be seated (e.g. in a vehicle), both in terms of the physical space available, and in terms of limitations set by law.\\\n\\\nTypical unit code(s): C62 for persons ",
    "o:id": 1290,
    "o:label": "seatingCapacity",
    "o:local_name": "seatingCapacity",
    "o:term": "schema:seatingCapacity",
    "o:vocabulary": {
        "@id": "https://kanazawabunko-db.pen-kanagawa.ed.jp/api/vocabularies/7",
        "o:id": 7
    }
}