{
    "@context": "https://kanazawabunko-db.pen-kanagawa.ed.jp/api-context",
    "@id": "https://kanazawabunko-db.pen-kanagawa.ed.jp/api/properties/951",
    "@type": "o:Property",
    "o:comment": "The specific biochemical interaction through which this drug or supplement produces its pharmacological effect.",
    "o:id": 951,
    "o:label": "mechanismOfAction",
    "o:local_name": "mechanismOfAction",
    "o:term": "schema:mechanismOfAction",
    "o:vocabulary": {
        "@id": "https://kanazawabunko-db.pen-kanagawa.ed.jp/api/vocabularies/7",
        "o:id": 7
    }
}